README.md
setup.py
src/libimg/__init__.py
src/libimg/equalize.py
src/libimg/geo.py
src/libimg/histogram.py
src/libimg/interpolate.py
src/libimg/mask.py
src/libimg.egg-info/PKG-INFO
src/libimg.egg-info/SOURCES.txt
src/libimg.egg-info/dependency_links.txt
src/libimg.egg-info/top_level.txt
src/libimg/channel/__init__.py
src/libimg/channel/masks.py
src/libimg/functional/__init__.py
src/libimg/functional/convolve.py
src/libimg/functional/transform.py
src/libimg/image/__init__.py
src/libimg/image/colorspace.py
src/libimg/image/image.py
src/libimg/math/__init__.py
src/libimg/math/ops.py