Metadata-Version: 1.0
Name: libimg
Version: 0.1.0
Summary: Library code for image processing
Home-page: UNKNOWN
Author: Matthew McRaven
Author-email: mkm302@georgetown.edu
License: UNKNOWN
Platform: UNKNOWN
